./.gitignore
./.python-version
./LICENSE
./PKG-INFO
./README.md
./main.py
./pyproject.toml
./setup.py
./text.txt
./src/cli.py
./src/utils.py
./src/commands/__init__.py
./src/commands/delete.py
./src/commands/ls.py
./src/commands/save.py
./src/commands/use.py
./src/completion/envm_complete.bash
./src/completion/envm_complete.fish
./src/completion/envm_complete.zsh
envm-0.1.3.dist-info/METADATA
envm-0.1.3.dist-info/WHEEL
envm-0.1.3.dist-info/entry_points.txt
envm-0.1.3.dist-info/licenses/LICENSE
envm-0.1.3.dist-info/RECORD
