Metadata-Version: 2.4
Name: envm
Version: 0.1.3
Summary: Environment Manager. CLI to manage environment variables. This tool was created to simplify working with multiple .env files across different projects and environments (development, staging, and local).
Project-URL: Homepage, https://github.com/emmanueloctavi0/envm
Project-URL: Issues, https://github.com/emmanueloctavi0/envm/issues
Author-email: Emmanuel Octavio <emmanueloctaviomc@gmail.com>
License: MIT
License-File: LICENSE
Classifier: Development Status :: 4 - Beta
Classifier: Environment :: Console
Classifier: Intended Audience :: Developers
Classifier: License :: OSI Approved :: MIT License
Classifier: Programming Language :: Python :: 3
Classifier: Programming Language :: Python :: 3.11
Requires-Python: >=3.11
Requires-Dist: click>=8.2.0
